Metadata-Version: 2.4
Name: willphanpy
Version: 0.3.2
Requires-Dist: numpy
Requires-Dist: matplotlib
Dynamic: description
Dynamic: description-content-type
Dynamic: requires-dist
